once_only/__init__.py
once_only-1.0.0.dist-info/LICENSE
once_only-1.0.0.dist-info/METADATA
once_only-1.0.0.dist-info/WHEEL
once_only-1.0.0.dist-info/top_level.txt
once_only-1.0.0.dist-info/RECORD
